{
    "Python Basics": { "prereqs": [], "level": "beginner", "domain": "tech" },
    "Python Advanced": { "prereqs": ["Python Basics"], "level": "intermediate", "domain": "tech" },
    "REST APIs": { "prereqs": ["Python Basics"], "level": "intermediate", "domain": "tech" },
    "FastAPI": { "prereqs": ["Python Advanced", "REST APIs"], "level": "advanced", "domain": "tech" },
    "Linux CLI": { "prereqs": [], "level": "beginner", "domain": "both" },
    "Docker": { "prereqs": ["Linux CLI"], "level": "intermediate", "domain": "tech" },
    "Kubernetes": { "prereqs": ["Docker"], "level": "advanced", "domain": "tech" },
    "CI/CD": { "prereqs": ["Docker", "Linux CLI"], "level": "intermediate", "domain": "tech" },
    "System Design": { "prereqs": ["Python Basics", "REST APIs"], "level": "advanced", "domain": "tech" },
    "WMS Basics": { "prereqs": [], "level": "beginner", "domain": "ops" },
    "SAP EWM": { "prereqs": ["WMS Basics"], "level": "advanced", "domain": "ops" },
    "Lean Six Sigma": { "prereqs": [], "level": "intermediate", "domain": "ops" },
    "KPI Analytics": { "prereqs": [], "level": "intermediate", "domain": "ops" },
    "Data Structures & Algorithms": { "prereqs": ["Python Basics"], "level": "intermediate", "domain": "tech" },
    "React Fundamentals": { "prereqs": [], "level": "beginner", "domain": "tech" },
    "State Management": { "prereqs": ["React Fundamentals"], "level": "intermediate", "domain": "tech" },
    "Advanced JavaScript Concepts": { "prereqs": [], "level": "advanced", "domain": "tech" },
    "Hazmat Handling": { "prereqs": [], "level": "advanced", "domain": "ops" },
    "Terraform Modules": { "prereqs": ["Linux CLI"], "level": "advanced", "domain": "tech" },
    "Go Programming": { "prereqs": ["Data Structures & Algorithms"], "level": "intermediate", "domain": "tech" },
    "Observability Patterns": { "prereqs": ["Linux CLI"], "level": "advanced", "domain": "tech" },
    "GraphQL Federation": { "prereqs": ["REST APIs"], "level": "advanced", "domain": "tech" },
    "Advanced Performance Patterns": { "prereqs": ["System Design"], "level": "advanced", "domain": "tech" }
}
